{
  "tests": {
    "example/tests/test_calculator.py::test_add_positive": {
      "outcome": "passed",
      "duration": 0.00018525001360103488,
      "requirement_ids": [
        "REQ-201"
      ],
      "surviving_mutants_count": 0,
      "is_weak": false
    },
    "example/tests/test_calculator.py::test_add_negative": {
      "outcome": "passed",
      "duration": 0.0001010000123642385,
      "requirement_ids": [
        "REQ-201"
      ],
      "surviving_mutants_count": 0,
      "is_weak": false
    },
    "example/tests/test_calculator.py::test_divide_by_zero_raises": {
      "outcome": "passed",
      "duration": 0.000329374975990504,
      "requirement_ids": [
        "REQ-202"
      ],
      "surviving_mutants_count": 0,
      "is_weak": false
    },
    "example/tests/test_calculator.py::test_multiply_positive": {
      "outcome": "passed",
      "duration": 9.062502067536116e-05,
      "requirement_ids": [
        "REQ-203"
      ],
      "surviving_mutants_count": 0,
      "is_weak": false
    },
    "example/tests/test_calculator.py::test_divide_normal": {
      "outcome": "passed",
      "duration": 8.754199370741844e-05,
      "requirement_ids": [
        "REQ-202"
      ],
      "surviving_mutants_count": 0,
      "is_weak": false
    }
  }
}